Downloads/Verilog Related Learning Material/taylor_poly.v
// =============================================================================
// taylor_poly.v
// Pipelined Taylor-Series Polynomial Evaluator (Horner's Method)
//
// Evaluates the degree-ORDER polynomial
//
//   P(x) = c0 + c1*(x-x0) + c2*(x-x0)^2 + ... + cN*(x-x0)^N
//
// where every c_k = f^(k)(x0) / k! is a pre-computed, fixed-point constant.
//
// Implementation uses Horner's method to avoid explicit power computation:
//
//   P(x) = c0 + dx*(c1 + dx*(c2 + ... + dx*(c_{N-1} + dx*cN)...))
//   dx    = x - x0
//
// Each Horner iteration occupies one pipeline stage, so the overall latency
// is ORDER + 1 clock cycles (one extra cycle to register dx and seed the
// accumulator with the highest-degree coefficient).
//
// ─── Fixed-point format ───────────────────────────────────────────────────────
//   All ports and parameters use signed Q(IW.FRAC_BITS) representation where
//   IW = DATA_WIDTH - FRAC_BITS - 1  (1 sign bit, IW magnitude bits, FRAC_BITS
//   fractional bits).
//
//   For the default DATA_WIDTH=32, FRAC_BITS=16 the representable range is
//   [-32768 , 32767.9999847...] with resolution 2^-16 ≈ 1.526e-5.
//
// ─── Coefficient packing ──────────────────────────────────────────────────────
//   COEFFS is a flat (MAX_ORDER+1)*DATA_WIDTH-bit vector.
//   Coefficient c_k occupies bits  [k*DATA_WIDTH +: DATA_WIDTH].
//   Pack the vector as  {c_{MAX_ORDER}, ..., c_1, c_0}  (c_0 at the LSBs).
//
// ─── Parameters ───────────────────────────────────────────────────────────────
//   DATA_WIDTH  Total bit-width of every data path (default 32).
//   FRAC_BITS   Fractional bits in the Q format     (default 16).
//   ORDER       Polynomial degree, 0 ≤ ORDER ≤ MAX_ORDER.
//   MAX_ORDER   Upper bound on ORDER; sizes the COEFFS array (default 7).
//   X0          Expansion point in fixed-point format.
//   COEFFS      Packed Taylor coefficients (see above).
// =============================================================================

`timescale 1ns/1ps

module taylor_poly #(
    parameter                                        DATA_WIDTH = 32,
    parameter                                        FRAC_BITS  = 16,
    parameter                                        ORDER      = 3,
    parameter                                        MAX_ORDER  = 7,
    parameter signed [DATA_WIDTH-1:0]                X0         = {DATA_WIDTH{1'b0}},
    parameter        [(MAX_ORDER+1)*DATA_WIDTH-1:0]  COEFFS     = {(MAX_ORDER+1)*DATA_WIDTH{1'b0}}
)(
    input  wire                         clk,
    input  wire                         rst_n,    // active-low synchronous reset
    input  wire                         valid_in,
    input  wire signed [DATA_WIDTH-1:0] x_in,
    output wire                         valid_out,
    output wire signed [DATA_WIDTH-1:0] y_out
);

    // -------------------------------------------------------------------------
    // Pipeline register arrays  (index 0 = stage 0, index ORDER = output stage)
    // -------------------------------------------------------------------------
    reg signed [DATA_WIDTH-1:0] dx_r  [0:ORDER];  // dx = x - x0 forwarded each stage
    reg signed [DATA_WIDTH-1:0] acc_r [0:ORDER];  // Horner accumulator
    reg                         vld_r [0:ORDER];  // valid token

    // ─── Stage 0: register dx and seed accumulator with c_ORDER ──────────────
    always @(posedge clk or negedge rst_n) begin
        if (!rst_n) begin
            dx_r[0]  <= {DATA_WIDTH{1'b0}};
            acc_r[0] <= {DATA_WIDTH{1'b0}};
            vld_r[0] <= 1'b0;
        end else begin
            dx_r[0]  <= x_in - X0;
            // Seed with the highest-degree Taylor coefficient c_ORDER.
            // The part-select is a constant expression at elaboration time.
            acc_r[0] <= COEFFS[ORDER*DATA_WIDTH +: DATA_WIDTH];
            vld_r[0] <= valid_in;
        end
    end

    // ─── Stages 1 … ORDER: Horner iterations ─────────────────────────────────
    // At stage i:
    //   acc = c_{ORDER-i}  +  dx * acc_prev
    //
    // Multiplication produces a 2*DATA_WIDTH-bit full-precision product in
    // Q(2*IW . 2*FRAC_BITS) format.  Truncating back to Q(IW.FRAC_BITS) is
    // achieved by discarding the lower FRAC_BITS bits:
    //   product_trunc = product[DATA_WIDTH+FRAC_BITS-1 : FRAC_BITS]
    // This retains the sign bit and DATA_WIDTH-1 lower magnitude/fraction bits.
    genvar i;
    generate
        for (i = 1; i <= ORDER; i = i + 1) begin : g_horner
            // Full-width signed product (no overflow loss at this width)
            wire signed [2*DATA_WIDTH-1:0] prod_full;
            // Product rounded back to the original Q format
            wire signed [DATA_WIDTH-1:0]   prod_trunc;
            // Taylor coefficient for this stage: c_{ORDER - i}
            wire signed [DATA_WIDTH-1:0]   coeff_k;

            assign coeff_k    = COEFFS[(ORDER-i)*DATA_WIDTH +: DATA_WIDTH];
            assign prod_full  = dx_r[i-1] * acc_r[i-1];
            assign prod_trunc = prod_full[DATA_WIDTH+FRAC_BITS-1 : FRAC_BITS];

            always @(posedge clk or negedge rst_n) begin
                if (!rst_n) begin
                    dx_r[i]  <= {DATA_WIDTH{1'b0}};
                    acc_r[i] <= {DATA_WIDTH{1'b0}};
                    vld_r[i] <= 1'b0;
                end else begin
                    dx_r[i]  <= dx_r[i-1];
                    acc_r[i] <= coeff_k + prod_trunc;
                    vld_r[i] <= vld_r[i-1];
                end
            end
        end
    endgenerate

    // ─── Output ───────────────────────────────────────────────────────────────
    assign y_out     = acc_r[ORDER];
    assign valid_out = vld_r[ORDER];

endmodule

Downloads/Verilog Related Learning Material/taylor_poly_tb.v
// =============================================================================
// taylor_poly_tb.v
// Testbench for taylor_poly.v   (Verilog-2001 compatible)
//
// Two DUT instances are exercised:
//
//  dut_quad  –  Exact quadratic  f(x) = x²  (ORDER=2, around x0=0)
//               c0=0, c1=0, c2=1.0 → P(x)=x², no approximation error.
//
//  dut_exp   –  e^x, 5-term series (ORDER=4, around x0=0)
//               c_k = 1/k!  for k=0..4
//
// Both DUTs share clock and reset.
// Results are verified using a real-valued expected-value shift register that
// accounts for the pipeline latency (ORDER + 1 cycles per DUT).
//
// Fixed-point format: signed Q(15.16)  →  scale = 65536.
// =============================================================================

`timescale 1ns/1ps

module taylor_poly_tb;

    // ─── Parameters & constants ───────────────────────────────────────────────
    localparam CLK_PERIOD = 10;   // ns
    localparam DW         = 32;   // DATA_WIDTH
    localparam FB         = 16;   // FRAC_BITS
    localparam SCALE      = 65536; // 1 << FB

    // Q16.16 coefficient literals
    localparam signed [DW-1:0] FP_1    = 32'h00010000; // 1.0
    localparam signed [DW-1:0] FP_HALF = 32'h00008000; // 0.5
    localparam signed [DW-1:0] FP_1_6  = 32'h00002AAB; // ≈1/6  (error<2^-16)
    localparam signed [DW-1:0] FP_1_24 = 32'h00000AAB; // ≈1/24 (error<2^-16)
    localparam signed [DW-1:0] FP_0    = 32'h00000000;

    // ─── Clock / reset ────────────────────────────────────────────────────────
    reg clk;
    reg rst_n;
    initial clk = 0;
    always #(CLK_PERIOD/2) clk = ~clk;

    // =========================================================================
    // DUT 1: f(x) = x²   ORDER=2, MAX_ORDER=7
    //   COEFFS: c0=0, c1=0, c2=1.0, c3..c7=0
    //   Packing: {c7, c6, c5, c4, c3, c2, c1, c0} → c0 at bits [31:0]
    // =========================================================================
    localparam QUAD_ORD = 2;
    localparam QUAD_MAX = 7;
    localparam QUAD_LAT = QUAD_ORD + 1; // pipeline latency in cycles

    localparam [(QUAD_MAX+1)*DW-1:0] QUAD_COEFFS =
        { FP_0,   // c7
          FP_0,   // c6
          FP_0,   // c5
          FP_0,   // c4
          FP_0,   // c3
          FP_1,   // c2 = 1.0
          FP_0,   // c1 = 0
          FP_0 }; // c0 = 0  (LSBs)

    reg                      quad_vin;
    reg  signed [DW-1:0]     quad_xin;
    wire                     quad_vout;
    wire signed [DW-1:0]     quad_yout;

    taylor_poly #(
        .DATA_WIDTH ( DW          ),
        .FRAC_BITS  ( FB          ),
        .ORDER      ( QUAD_ORD    ),
        .MAX_ORDER  ( QUAD_MAX    ),
        .X0         ( FP_0        ),
        .COEFFS     ( QUAD_COEFFS )
    ) dut_quad (
        .clk       ( clk       ),
        .rst_n     ( rst_n     ),
        .valid_in  ( quad_vin  ),
        .x_in      ( quad_xin  ),
        .valid_out ( quad_vout ),
        .y_out     ( quad_yout )
    );

    // =========================================================================
    // DUT 2: e^x  5-term  ORDER=4, MAX_ORDER=7
    //   c0=1, c1=1, c2=1/2, c3=1/6, c4=1/24
    // =========================================================================
    localparam EXP_ORD = 4;
    localparam EXP_MAX = 7;
    localparam EXP_LAT = EXP_ORD + 1;

    localparam [(EXP_MAX+1)*DW-1:0] EXP_COEFFS =
        { FP_0,      // c7  bits[255:224]
          FP_0,      // c6  bits[223:192]
          FP_0,      // c5  bits[191:160]
          FP_1_24,   // c4  bits[159:128]
          FP_1_6,    // c3  bits[127:96]
          FP_HALF,   // c2  bits[95:64]
          FP_1,      // c1  bits[63:32]
          FP_1 };    // c0  bits[31:0]

    reg                      exp_vin;
    reg  signed [DW-1:0]     exp_xin;
    wire                     exp_vout;
    wire signed [DW-1:0]     exp_yout;

    taylor_poly #(
        .DATA_WIDTH ( DW         ),
        .FRAC_BITS  ( FB         ),
        .ORDER      ( EXP_ORD    ),
        .MAX_ORDER  ( EXP_MAX    ),
        .X0         ( FP_0       ),
        .COEFFS     ( EXP_COEFFS )
    ) dut_exp (
        .clk       ( clk       ),
        .rst_n     ( rst_n     ),
        .valid_in  ( exp_vin   ),
        .x_in      ( exp_xin   ),
        .valid_out ( exp_vout  ),
        .y_out     ( exp_yout  )
    );

    // ─── Fixed-point conversion helpers ──────────────────────────────────────
    // Convert signed Q16.16 to real
    function real fp_to_real;
        input signed [DW-1:0] fp;
        begin
            fp_to_real = $itor(fp) / $itor(SCALE);
        end
    endfunction

    // Convert real to nearest signed Q16.16
    function signed [DW-1:0] real_to_fp;
        input real r;
        begin
            real_to_fp = $rtoi(r * $itor(SCALE));
        end
    endfunction

    // ─── Module-level stimulus and expected-value tables ─────────────────────
    // ── Quadratic test vectors (7 samples) ───────────────────────────────────
    localparam QUAD_N = 7;
    reg signed [DW-1:0] qx [0:QUAD_N-1];
    real                qe [0:QUAD_N-1];  // expected: x²

    // ── e^x test vectors (6 samples) ─────────────────────────────────────────
    localparam EXP_N = 6;
    reg signed [DW-1:0] ex [0:EXP_N-1];
    real                ee [0:EXP_N-1];  // expected: 5-term polynomial value

    // ─── Expected-value shift registers ──────────────────────────────────────
    real quad_sr [0:QUAD_LAT-1]; // depth = latency
    real exp_sr  [0:EXP_LAT-1];

    // ─── Pass / fail counters ─────────────────────────────────────────────────
    integer pass_cnt, fail_cnt;

    // ─── Loop variables (module scope for Verilog-2001 compatibility) ─────────
    integer qi, ei, j;

    // ─── Checker tasks ────────────────────────────────────────────────────────
    task check_quad;
        input real expected;
        real got, err;
        begin
            got = fp_to_real(quad_yout);
            err = (got > expected) ? (got - expected) : (expected - got);
            // Tolerate 1 LSB of rounding (2^-16)
            if (err <= (2.0 / $itor(SCALE))) begin
                $display("  [QUAD PASS]  x^2 :  y = %10.6f  (expected %10.6f)",
                         got, expected);
                pass_cnt = pass_cnt + 1;
            end else begin
                $display("  [QUAD FAIL]  x^2 :  y = %10.6f  (expected %10.6f)  err=%e",
                         got, expected, err);
                fail_cnt = fail_cnt + 1;
            end
        end
    endtask

    task check_exp;
        input real expected;
        real got, err;
        begin
            got = fp_to_real(exp_yout);
            err = (got > expected) ? (got - expected) : (expected - got);
            // Accumulated rounding over 5 stages: allow a few LSBs
            if (err <= (16.0 / $itor(SCALE))) begin
                $display("  [EXP  PASS]  e^x :  y = %10.6f  (expected %10.6f)",
                         got, expected);
                pass_cnt = pass_cnt + 1;
            end else begin
                $display("  [EXP  FAIL]  e^x :  y = %10.6f  (expected %10.6f)  err=%e",
                         got, expected, err);
                fail_cnt = fail_cnt + 1;
            end
        end
    endtask

    // ─── Stimulus ─────────────────────────────────────────────────────────────
    initial begin
        // ── Populate stimulus tables ──────────────────────────────────────────
        // Quadratic: expected = x²
        qx[0] = real_to_fp(-3.0); qe[0] =  9.0;
        qx[1] = real_to_fp(-2.0); qe[1] =  4.0;
        qx[2] = real_to_fp(-1.0); qe[2] =  1.0;
        qx[3] = real_to_fp( 0.0); qe[3] =  0.0;
        qx[4] = real_to_fp( 1.0); qe[4] =  1.0;
        qx[5] = real_to_fp( 2.0); qe[5] =  4.0;
        qx[6] = real_to_fp( 3.0); qe[6] =  9.0;

        // e^x 5-term: expected = 1 + x + x²/2 + x³/6 + x⁴/24
        ex[0] = real_to_fp(-1.0);
        ee[0] = 1.0 + (-1.0) + (1.0/2.0) + (-1.0/6.0) + (1.0/24.0); // ≈0.375

        ex[1] = real_to_fp(0.0);
        ee[1] = 1.0;

        ex[2] = real_to_fp(0.5);
        ee[2] = 1.0 + 0.5 + 0.125 + (0.125/6.0) + (0.0625/24.0);    // ≈1.6484

        ex[3] = real_to_fp(1.0);
        ee[3] = 1.0 + 1.0 + 0.5 + (1.0/6.0) + (1.0/24.0);            // ≈2.7083

        ex[4] = real_to_fp(2.0);
        ee[4] = 1.0 + 2.0 + 2.0 + (8.0/6.0) + (16.0/24.0);           // ≈7.0

        ex[5] = real_to_fp(0.25);
        ee[5] = 1.0 + 0.25 + 0.03125 + (0.015625/6.0) + (0.00390625/24.0);

        // ── VCD waveform dump ─────────────────────────────────────────────────
        $dumpfile("taylor_poly.vcd");
        $dumpvars(0, taylor_poly_tb);

        // ── Initialise shift registers and counters ───────────────────────────
        for (j = 0; j < QUAD_LAT; j = j + 1) quad_sr[j] = 0.0;
        for (j = 0; j < EXP_LAT;  j = j + 1) exp_sr[j]  = 0.0;
        pass_cnt = 0;
        fail_cnt = 0;

        // ── Reset ─────────────────────────────────────────────────────────────
        rst_n    = 0;
        quad_vin = 0;  quad_xin = 0;
        exp_vin  = 0;  exp_xin  = 0;
        repeat (4) @(posedge clk);
        @(negedge clk); rst_n = 1;

        // ─────────────────────────────────────────────────────────────────────
        $display("=============================================================");
        $display("  Taylor Polynomial Evaluator – Simulation");
        $display("  Format: signed Q%0d.%0d   scale = %0d", DW-FB-1, FB, SCALE);
        $display("=============================================================");

        // ── Run DUT 1 (quadratic) ─────────────────────────────────────────────
        $display("\n--- DUT 1: f(x) = x^2  (ORDER=%0d, latency=%0d cycles) ---",
                 QUAD_ORD, QUAD_LAT);

        exp_vin = 0; exp_xin = 0;

        for (qi = 0; qi < QUAD_N + QUAD_LAT; qi = qi + 1) begin
            @(negedge clk);

            // Drive input while samples remain
            if (qi < QUAD_N) begin
                quad_xin = qx[qi];
                quad_vin = 1;
            end else begin
                quad_vin = 0;
            end

            // Shift expected-value pipeline (oldest at index QUAD_LAT-1)
            for (j = QUAD_LAT-1; j > 0; j = j - 1)
                quad_sr[j] = quad_sr[j-1];
            quad_sr[0] = (qi < QUAD_N) ? qe[qi] : 0.0;

            // Check output one delta after posedge (register values settled)
            @(posedge clk); #1;
            if (quad_vout)
                check_quad(quad_sr[QUAD_LAT-1]);
        end

        quad_vin = 0;

        // ── Run DUT 2 (e^x) ──────────────────────────────────────────────────
        $display("\n--- DUT 2: e^x (5-term, ORDER=%0d, latency=%0d cycles) ---",
                 EXP_ORD, EXP_LAT);

        for (ei = 0; ei < EXP_N + EXP_LAT; ei = ei + 1) begin
            @(negedge clk);

            if (ei < EXP_N) begin
                exp_xin = ex[ei];
                exp_vin = 1;
            end else begin
                exp_vin = 0;
            end

            for (j = EXP_LAT-1; j > 0; j = j - 1)
                exp_sr[j] = exp_sr[j-1];
            exp_sr[0] = (ei < EXP_N) ? ee[ei] : 0.0;

            @(posedge clk); #1;
            if (exp_vout)
                check_exp(exp_sr[EXP_LAT-1]);
        end

        // ── Summary ───────────────────────────────────────────────────────────
        $display("\n=============================================================");
        $display("  Results:  %0d PASSED  /  %0d FAILED", pass_cnt, fail_cnt);
        if (fail_cnt == 0)
            $display("  ALL TESTS PASSED");
        else
            $display("  *** FAILURES DETECTED ***");
        $display("=============================================================");

        $finish;
    end

    // ─── Timeout watchdog ─────────────────────────────────────────────────────
    initial begin
        #100000;
        $display("TIMEOUT");
        $finish;
    end

endmodule

Downloads/Verilog Related Learning Material/taylor_poly.vcd
$date
	Fri Feb 27 22:54:06 2026
$end
$version
	Icarus Verilog
$end
$timescale
	1ps
$end
$scope module taylor_poly_tb $end
$var wire 32 ! quad_yout [31:0] $end
$var wire 1 " quad_vout $end
$var wire 32 # exp_yout [31:0] $end
$var wire 1 $ exp_vout $end
$var parameter 32 % CLK_PERIOD $end
$var parameter 32 & DW $end
$var parameter 256 ' EXP_COEFFS $end
$var parameter 33 ( EXP_LAT $end
$var parameter 32 ) EXP_MAX $end
$var parameter 32 * EXP_N $end
$var parameter 32 + EXP_ORD $end
$var parameter 32 , FB $end
$var parameter 32 - FP_0 $end
$var parameter 32 . FP_1 $end
$var parameter 32 / FP_1_24 $end
$var parameter 32 0 FP_1_6 $end
$var parameter 32 1 FP_HALF $end
$var parameter 256 2 QUAD_COEFFS $end
$var parameter 33 3 QUAD_LAT $end
$var parameter 32 4 QUAD_MAX $end
$var parameter 32 5 QUAD_N $end
$var parameter 32 6 QUAD_ORD $end
$var parameter 32 7 SCALE $end
$var reg 1 8 clk $end
$var reg 1 9 exp_vin $end
$var reg 32 : exp_xin [31:0] $end
$var reg 1 ; quad_vin $end
$var reg 32 < quad_xin [31:0] $end
$var reg 1 = rst_n $end
$var integer 32 > ei [31:0] $end
$var integer 32 ? fail_cnt [31:0] $end
$var integer 32 @ j [31:0] $end
$var integer 32 A pass_cnt [31:0] $end
$var integer 32 B qi [31:0] $end
$scope function fp_to_real $end
$var reg 32 C fp [31:0] $end
$upscope $end
$scope function real_to_fp $end
$var real 1 D r $end
$upscope $end
$scope module dut_exp $end
$var wire 1 8 clk $end
$var wire 1 = rst_n $end
$var wire 1 9 valid_in $end
$var wire 1 $ valid_out $end
$var wire 32 E x_in [31:0] $end
$var wire 32 F y_out [31:0] $end
$var parameter 256 G COEFFS $end
$var parameter 32 H DATA_WIDTH $end
$var parameter 32 I FRAC_BITS $end
$var parameter 32 J MAX_ORDER $end
$var parameter 32 K ORDER $end
$var parameter 32 L X0 $end
$scope begin g_horner[1] $end
$var wire 32 M coeff_k [31:0] $end
$var wire 32 N prod_trunc [31:0] $end
$var wire 64 O prod_full [63:0] $end
$var parameter 2 P i $end
$upscope $end
$scope begin g_horner[2] $end
$var wire 32 Q coeff_k [31:0] $end
$var wire 32 R prod_trunc [31:0] $end
$var wire 64 S prod_full [63:0] $end
$var parameter 3 T i $end
$upscope $end
$scope begin g_horner[3] $end
$var wire 32 U coeff_k [31:0] $end
$var wire 32 V prod_trunc [31:0] $end
$var wire 64 W prod_full [63:0] $end
$var parameter 3 X i $end
$upscope $end
$scope begin g_horner[4] $end
$var wire 32 Y coeff_k [31:0] $end
$var wire 32 Z prod_trunc [31:0] $end
$var wire 64 [ prod_full [63:0] $end
$var parameter 4 \ i $end
$upscope $end
$upscope $end
$scope module dut_quad $end
$var wire 1 8 clk $end
$var wire 1 = rst_n $end
$var wire 1 ; valid_in $end
$var wire 1 " valid_out $end
$var wire 32 ] x_in [31:0] $end
$var wire 32 ^ y_out [31:0] $end
$var parameter 256 _ COEFFS $end
$var parameter 32 ` DATA_WIDTH $end
$var parameter 32 a FRAC_BITS $end
$var parameter 32 b MAX_ORDER $end
$var parameter 32 c ORDER $end
$var parameter 32 d X0 $end
$scope begin g_horner[1] $end
$var wire 32 e coeff_k [31:0] $end
$var wire 32 f prod_trunc [31:0] $end
$var wire 64 g prod_full [63:0] $end
$var parameter 2 h i $end
$upscope $end
$scope begin g_horner[2] $end
$var wire 32 i coeff_k [31:0] $end
$var wire 32 j prod_trunc [31:0] $end
$var wire 64 k prod_full [63:0] $end
$var parameter 3 l i $end
$upscope $end
$upscope $end
$scope task check_exp $end
$var real 1 m err $end
$var real 1 n expected $end
$var real 1 o got $end
$upscope $end
$scope task check_quad $end
$var real 1 p err $end
$var real 1 q expected $end
$var real 1 r got $end
$upscope $end
$upscope $end
$enddefinitions $end
$comment Show the parameter values. $end
$dumpall
b10 l
b1 h
b0 d
b10 c
b111 b
b10000 a
b100000 `
b100000000000000000000000000000000000000000000000000000000000000000000000000000000 _
b100 \
b11 X
b10 T
b1 P
b0 L
b100 K
b111 J
b10000 I
b100000 H
b10101010101100000000000000000010101010101011000000000000000010000000000000000000000000000001000000000000000000000000000000010000000000000000 G
b10000000000000000 7
b10 6
b111 5
b111 4
b11 3
b100000000000000000000000000000000000000000000000000000000000000000000000000000000 2
b1000000000000000 1
b10101010101011 0
b101010101011 /
b10000000000000000 .
b0 -
b10000 ,
b100 +
b110 *
b111 )
b101 (
b10101010101100000000000000000010101010101011000000000000000010000000000000000000000000000001000000000000000000000000000000010000000000000000 '
b100000 &
b1010 %
$end
#0
$dumpvars
r0 r
r0 q
r0 p
r0 o
r0 n
r0 m
b0 k
b0 j
b0 i
b0 g
b0 f
b0 e
b0 ^
b0 ]
b0 [
b0 Z
b10000000000000000 Y
b0 W
b0 V
b10000000000000000 U
b0 S
b0 R
b1000000000000000 Q
b0 O
b0 N
b10101010101011 M
b0 F
b0 E
r0.25 D
bx C
bx B
b0 A
b101 @
b0 ?
bx >
0=
b0 <
0;
b0 :
09
08
0$
b0 #
0"
b0 !
$end
#5000
18
#10000
08
#15000
18
#20000
08
#25000
18
#30000
08
#35000
18
#40000
b0 B
1=
08
#45000
b10000000000000000 #
b10000000000000000 F
18
#50000
b0 @
1;
b11111111111111010000000000000000 <
b11111111111111010000000000000000 ]
08
#55000
b11111111111111010000000000000000 f
b1111111111111111111111111111110100000000000000000000000000000000 g
18
#56000
b1 B
#60000
b0 @
b11111111111111100000000000000000 <
b11111111111111100000000000000000 ]
08
#65000
b11111111111111100000000000000000 f
b10010000000000000000 j
b1111111111111111111111111111111000000000000000000000000000000000 g
b100100000000000000000000000000000000 k
18
#66000
b10 B
#70000
b0 @
b11111111111111110000000000000000 <
b11111111111111110000000000000000 ]
08
#75000
b1000000000000000000 j
b11111111111111110000000000000000 f
b10000000000000000000000000000000000 k
1"
b10010000000000000000 !
b10010000000000000000 ^
b1111111111111111111111111111111100000000000000000000000000000000 g
18
#76000
b11 B
b1 A
r9 r
b10010000000000000000 C
r9 q
#80000
b0 @
b0 <
b0 ]
08
#85000
b0 f
b10000000000000000 j
b0 g
b1000000000000000000 !
b1000000000000000000 ^
b100000000000000000000000000000000 k
18
#86000
b100 B
b10 A
r4 r
b1000000000000000000 C
r4 q
#90000
b0 @
b10000000000000000 <
b10000000000000000 ]
08
#95000
b0 j
b10000000000000000 f
b0 k
b10000000000000000 !
b10000000000000000 ^
b100000000000000000000000000000000 g
18
#96000
b101 B
b11 A
r1 r
b10000000000000000 C
r1 q
#100000
b0 @
b100000000000000000 <
b100000000000000000 ]
08
#105000
b100000000000000000 f
b10000000000000000 j
b1000000000000000000000000000000000 g
b0 !
b0 ^
b100000000000000000000000000000000 k
18
#106000
b110 B
b100 A
r0 r
b0 C
r0 q
#110000
b0 @
b110000000000000000 <
b110000000000000000 ]
08
#115000
b1000000000000000000 j
b110000000000000000 f
b10000000000000000000000000000000000 k
b10000000000000000 !
b10000000000000000 ^
b1100000000000000000000000000000000 g
18
#116000
b111 B
b101 A
r1 r
b10000000000000000 C
r1 q
#120000
b0 @
0;
08
#125000
b10010000000000000000 j
b1000000000000000000 !
b1000000000000000000 ^
b100100000000000000000000000000000000 k
18
#126000
b1000 B
b110 A
r4 r
b1000000000000000000 C
r4 q
#130000
b0 @
08
#135000
b10010000000000000000 !
b10010000000000000000 ^
18
#136000
b1001 B
b111 A
r9 r
b10010000000000000000 C
r9 q
#140000
b0 @
08
#145000
0"
18
#146000
b0 >
b1010 B
#150000
b0 @
19
b11111111111111110000000000000000 :
b11111111111111110000000000000000 E
08
#155000
b11111111111111111111010101010101 N
b1111111111111111111111111111111111110101010101010000000000000000 O
18
#156000
b1 >
#160000
b0 @
b0 :
b0 E
08
#165000
b0 N
b11111111111111111110000000000000 R
b0 O
b1111111111111111111111111111111111100000000000000000000000000000 S
18
#166000
b10 >
#170000
b0 @
b1000000000000000 :
b1000000000000000 E
08
#175000
b0 R
b11111111111111111010000000000000 V
b10101010101 N
b0 S
b1111111111111111111111111111111110100000000000000000000000000000 W
b101010101011000000000000000 O
18
#176000
b11 >
#180000
b0 @
b10000000000000000 :
b10000000000000000 E
08
#185000
b101010101011 N
b11111111111111110110000000000000 Z
b0 V
b1100000000000 R
b1010101010110000000000000000 O
b1111111111111111111111111111111101100000000000000000000000000000 [
b0 W
b11000000000000000000000000000 S
18
#186000
b100 >
#190000
b0 @
b100000000000000000 :
b100000000000000000 E
08
#195000
b11010101010110 R
b100110000000000 V
b0 Z
b1010101010110 N
b110101010101100000000000000000 S
b1001100000000000000000000000000 W
b0 [
1$
b110000000000000 #
b110000000000000 F
b10101010101100000000000000000 O
18
#196000
b101 >
b1000 A
r5.551115123125783e-17 m
r0.375 o
b110000000000000 C
r0.3750000000000001 n
#200000
b0 @
b100000000000000 :
b100000000000000 E
08
#205000
b1010101010 N
b1010011000000000 Z
b1011010101010110 V
b1000000000000010 R
b10101010101100000000000000 O
b10000000000000000 #
b10000000000000000 F
b10100110000000000000000000000000 [
b10110101010101100000000000000000 W
b10000000000000100000000000000000 S
18
#206000
b110 >
b1001 A
r0 m
r1 o
b10000000000000000 C
r1 n
#210000
b0 @
09
08
#215000
b101101010101 R
b100000000000000100 V
b11011010101010110 Z
b1011010101010100000000000000 S
b1000000000000001000000000000000000 W
b110110101010101100000000000000000 [
b11010011000000000 #
b11010011000000000 F
18
#216000
b111 >
b1010 A
r1.6484375 o
b11010011000000000 C
r1.6484375 n
#220000
b0 @
08
#225000
b1100000000000001000 Z
b10001011010101 V
b101011010101010110 #
b101011010101010110 F
b11000000000000010000000000000000000 [
b100010110101010100000000000000 W
18
#226000
b1000 >
b1011 A
r1.017252604196273e-05 m
r2.708343505859375 o
b101011010101010110 C
r2.708333333333333 n
#230000
b0 @
08
#235000
b100100010110101 Z
b1001000101101010100000000000000 [
b1110000000000001000 #
b1110000000000001000 F
18
#236000
b1001 >
b1100 A
r0.0001220703125 m
r7.0001220703125 o
b1110000000000001000 C
r7 n
#240000
b0 @
08
#245000
b10100100010110101 #
b10100100010110101 F
18
#246000
b1010 >
b1101 A
r5.086263020981363e-06 m
r1.284011840820312 o
b10100100010110101 C
r1.284016927083333 n
#250000
b0 @
08
#255000
0$
18
#256000
b1011 >
